boundless/__init__.py
boundless/__main__.py
boundless/authorization.py
boundless/cli.py
boundless/client.py
boundless/deferred.py
boundless/errors.py
boundless/function.py
boundless/permission.py
boundless/registry.py
boundless/request.py
boundless/response.py
boundless/server.py
boundless/status.py
boundless/validators.py
boundless/serializer/__init__.py
boundless/serializer/deserialize.py
boundless/serializer/serialize.py
boundless/transport/__init__.py
boundless/transport/client/__init__.py
boundless/transport/client/aio_http_client_transport.py
boundless/transport/client/jet_client_transport.py
boundless/transport/server/__init__.py
boundless/transport/server/aio_http_server_transport.py
boundless/transport/server/jet_server_transport.py
boundless-0.1.2.data/scripts/brpc
tests/__init__.py
tests/test_function.py
tests/test_registry.py
tests/test_validators.py
tests/functions/__init__.py
tests/functions/one/__init__.py
tests/functions/one/two.py
boundless-0.1.2.dist-info/LICENSE.md
boundless-0.1.2.dist-info/METADATA
boundless-0.1.2.dist-info/WHEEL
boundless-0.1.2.dist-info/top_level.txt
boundless-0.1.2.dist-info/RECORD
